lpm/__init__.py
lpm/__main__.py
lpm/commandline.py
lpm/config.py
lpm/game.py
lpm/screen.py
lpm/snippets.py
lpm/stats.py
lpm-0.0.9.dist-info/LICENSE.txt
lpm-0.0.9.dist-info/METADATA
lpm-0.0.9.dist-info/WHEEL
lpm-0.0.9.dist-info/entry_points.txt
lpm-0.0.9.dist-info/top_level.txt
lpm-0.0.9.dist-info/zip-safe
lpm-0.0.9.dist-info/RECORD
