Metadata-Version: 2.1
Name: lpm
Version: 0.0.9
Summary: Command line application for practicing coding speed.
Home-page: https://gitlab.cas.mcmaster.ca/modyj/3xa3.git
Author: Jay Mody, Jessica Lim, Maanav Dalal
Author-email: jaykmody@gmail.com, jessicalim813@gmail.com, maanavdalal@gmail.com
License: https://www.gnu.org/licenses/agpl-3.0.html
Keywords: lpm,typing,typist,code,keyboard
Platform: unix
Platform: linux
Platform: osx
Platform: cygwin
Classifier: Environment :: Console
Classifier: Natural Language :: English
Classifier: Operating System :: MacOS :: MacOS X
Classifier: Operating System :: Microsoft :: Windows
Classifier: Operating System :: POSIX
Classifier: Operating System :: Unix
Classifier: Programming Language :: Python
Classifier: Programming Language :: Python :: 2
Classifier: Programming Language :: Python :: 3
Classifier: Programming Language :: Python :: Implementation :: PyPy
Requires-Dist: setuptools
Requires-Dist: windows-curses (>=2.2.0) ; platform_system == "Windows"
